pdfdol/__init__.py
pdfdol/base.py
pdfdol/tools.py
pdfdol/util.py
pdfdol/examples/__init__.py
pdfdol/examples/aggregations.py
pdfdol/tests/__init__.py
pdfdol/tests/test_base.py
pdfdol/tests/test_tools.py
pdfdol/tests/utils_for_testing.py
pdfdol-0.1.22.dist-info/LICENSE
pdfdol-0.1.22.dist-info/METADATA
pdfdol-0.1.22.dist-info/WHEEL
pdfdol-0.1.22.dist-info/top_level.txt
pdfdol-0.1.22.dist-info/RECORD
