Metadata-Version: 2.1
Name: pdfdol
Version: 0.1.22
Summary: Data Object Layer for PDF data
License: mit
License-File: LICENSE
Requires-Dist: dol
Requires-Dist: pypdf
Requires-Dist: markdown
Requires-Dist: pdfkit
